pythonImager/__init__.py
pythonImager/__vars__.py
pythonImager/calculs.py
pythonImager/colors.py
pythonImager/main.py
pythonImager/resolution.py
pythonImager/terminal_colors.py
pythonImager/fonts/default.ttf
python_imager-1.4.48.dist-info/licenses/LICENCE
test/layouts_test.py
test/text_test.py
test/trackbar_test.py
python_imager-1.4.48.dist-info/METADATA
python_imager-1.4.48.dist-info/WHEEL
python_imager-1.4.48.dist-info/top_level.txt
python_imager-1.4.48.dist-info/RECORD
