Metadata-Version: 2.4
Name: python-imager
Version: 1.4.48
Summary: Python image program
Author-email: Rigavid <rigavid.code@gmail.com>
License-Expression: MIT
Project-URL: Repository, https://github.com/rigavid/python-imager
Project-URL: Issues, https://github.com/rigavid/python-imager/issues
Keywords: python,image
Classifier: Programming Language :: Python :: 3
Requires-Python: >=3.12
License-File: LICENCE
Requires-Dist: numpy
Requires-Dist: opencv-python
Requires-Dist: screeninfo
Requires-Dist: pillow
Dynamic: license-file
